mq_utils/__init__.py
mq_utils/adb_utils.py
mq_utils/date_utils.py
mq_utils/db_utils.py
mq_utils/mqpool_utils.py
mq_utils/odps_utils.py
mq_utils/oss_utils.py
mq_utils/utils.py
mq_utils_lance-0.0.11.dist-info/LICENSE
mq_utils_lance-0.0.11.dist-info/METADATA
mq_utils_lance-0.0.11.dist-info/WHEEL
mq_utils_lance-0.0.11.dist-info/top_level.txt
mq_utils_lance-0.0.11.dist-info/RECORD
