Metadata-Version: 2.1
Name: mq-utils-lance
Version: 0.0.11
Summary: common utils
Home-page: https://github.com/LanceLand
Author: lance.txl
Author-email: tankcater@126.com
License: UNKNOWN
Project-URL: Bug Tracker, https://github.com/LanceLand
Platform: UNKNOWN
Classifier: Programming Language :: Python :: 3
Classifier: License :: OSI Approved :: MIT License
Classifier: Operating System :: OS Independent
Requires-Python: >=3.6
License-File: LICENSE
Requires-Dist: pymysql
Requires-Dist: opencv-python
Requires-Dist: requests
Requires-Dist: oss2
